dais_sdk/__init__.py
dais_sdk/debug.py
dais_sdk/logger.py
dais_sdk/param_parser.py
dais_sdk/stream.py
dais_sdk/mcp_client/__init__.py
dais_sdk/mcp_client/base_mcp_client.py
dais_sdk/mcp_client/local_mcp_client.py
dais_sdk/mcp_client/oauth_server.py
dais_sdk/mcp_client/remote_mcp_client.py
dais_sdk/tool/__init__.py
dais_sdk/tool/execute.py
dais_sdk/tool/prepare.py
dais_sdk/tool/utils.py
dais_sdk/tool/toolset/__init__.py
dais_sdk/tool/toolset/mcp_toolset.py
dais_sdk/tool/toolset/python_toolset.py
dais_sdk/tool/toolset/toolset.py
dais_sdk/types/__init__.py
dais_sdk/types/exceptions.py
dais_sdk/types/message.py
dais_sdk/types/request_params.py
dais_sdk/types/tool.py
dais_sdk-0.6.2.dist-info/licenses/LICENSE
dais_sdk-0.6.2.dist-info/WHEEL
dais_sdk-0.6.2.dist-info/METADATA
dais_sdk-0.6.2.dist-info/RECORD
