Metadata-Version: 2.4
Name: dais-sdk
Version: 0.6.2
Summary: A wrapper of LiteLLM
Author-email: BHznJNs <bhznjns@outlook.com>
Requires-Python: >=3.14
Classifier: Development Status :: 3 - Alpha
Classifier: Intended Audience :: Developers
Classifier: License :: OSI Approved :: MIT License
Classifier: Programming Language :: Python :: 3 :: Only
Classifier: Programming Language :: Python :: 3.14
License-File: LICENSE
Requires-Dist: litellm>=1.80.0
Requires-Dist: pydantic>=2.0.0
Requires-Dist: httpx==0.28.1
Requires-Dist: mcp==1.25.0
Requires-Dist: starlette==0.50.0
Requires-Dist: uvicorn==0.40.0
Project-URL: Source, https://github.com/Dais-Project/Dais-SDK
Project-URL: Tracker, https://github.com/Dais-Project/Dais-SDK/issues
